dline
