Metadata-Version: 2.1
Name: dline
Version: 2.3.0
Summary: A feature-rich terminal discord client
Home-page: https://github.com/NatTupper/dline
Author: Nat Osaka
Author-email: natthetupper@gmail.com
License: gpl-3.0
Keywords: discord,discord.py,chat client,ncurses
Platform: UNKNOWN
Classifier: Development Status :: 4 - Beta
Classifier: Intended Audience :: End Users/Desktop
Classifier: License :: OSI Approved :: GNU General Public License v3 (GPLv3)
Classifier: Programming Language :: Python :: 3
Classifier: Programming Language :: Python :: 3.5
Classifier: Programming Language :: Python :: 3.6
Classifier: Programming Language :: Python :: 3.7
Classifier: Topic :: Communications :: Chat
